ceda_sentinel_dhs_tools/__init__.py
ceda_sentinel_dhs_tools/create_producer_consumer.py
ceda_sentinel_dhs_tools/delete_producer_consumer.py
ceda_sentinel_dhs_tools/list_producer_consumers.py
ceda_sentinel_dhs_tools/templates/.gitkeep
ceda_sentinel_dhs_tools/templates/colhub2_gss_consumer.json
ceda_sentinel_dhs_tools/templates/colhub2_gss_producer.json
ceda_sentinel_dhs_tools-0.1.2.dist-info/METADATA
ceda_sentinel_dhs_tools-0.1.2.dist-info/WHEEL
ceda_sentinel_dhs_tools-0.1.2.dist-info/entry_points.txt
ceda_sentinel_dhs_tools-0.1.2.dist-info/RECORD
