Metadata-Version: 2.3
Name: ceda-sentinel-dhs-tools
Version: 0.1.2
Summary: Tools for managing CEDA Sentinel DHS
License: MIT
Author: Edbo849
Author-email: edborthwick84@gmail.com
Requires-Python: >=3.9,<4.0
Classifier: License :: OSI Approved :: MIT License
Classifier: Programming Language :: Python :: 3
Classifier: Programming Language :: Python :: 3.9
Classifier: Programming Language :: Python :: 3.10
Classifier: Programming Language :: Python :: 3.11
Classifier: Programming Language :: Python :: 3.12
Classifier: Programming Language :: Python :: 3.13
Requires-Dist: click (>=8.1.8,<9.0.0)
Requires-Dist: importlib_resources (>=6.0.0,<7.0.0)
Requires-Dist: jinja2 (>=3.1.5,<4.0.0)
Requires-Dist: requests (>=2.32.3,<3.0.0)
Requires-Dist: tabulate (>=0.9.0,<0.10.0)
